LICENSE.txt
MANIFEST.in
README.rst
setup.py
algorithm_mic_sdk/__init__.py
algorithm_mic_sdk/auth.py
algorithm_mic_sdk/base.py
algorithm_mic_sdk/error.py
algorithm_mic_sdk/response.py
algorithm_mic_sdk/tools.py
algorithm_mic_sdk/ws_base.py
algorithm_mic_sdk/algorithms/__init__.py
algorithm_mic_sdk/algorithms/cartoon_portrait.py
algorithm_mic_sdk/algorithms/check_photo_classic.py
algorithm_mic_sdk/algorithms/clear_noise.py
algorithm_mic_sdk/algorithms/cutout_and_beauty.py
algorithm_mic_sdk/algorithms/doc_correct.py
algorithm_mic_sdk/algorithms/double_picture_stitching.py
algorithm_mic_sdk/algorithms/extract_face_feature.py
algorithm_mic_sdk/algorithms/face_info_classic.py
algorithm_mic_sdk/algorithms/face_retouch.py
algorithm_mic_sdk/algorithms/facial_beauty.py
algorithm_mic_sdk/algorithms/facial_beauty_short.py
algorithm_mic_sdk/algorithms/fluorescent_pen_recognition.py
algorithm_mic_sdk/algorithms/font_generation.py
algorithm_mic_sdk/algorithms/foreign_matter_removal.py
algorithm_mic_sdk/algorithms/foreign_matter_removal_pro.py
algorithm_mic_sdk/algorithms/gpu_accelerate.py
algorithm_mic_sdk/algorithms/handwritten_re_field.py
algorithm_mic_sdk/algorithms/head_front.py
algorithm_mic_sdk/algorithms/human_plus_classic.py
algorithm_mic_sdk/algorithms/id_eshader.py
algorithm_mic_sdk/algorithms/idphoto_deep_beauty_to_b.py
algorithm_mic_sdk/algorithms/image_handle_classic.py
algorithm_mic_sdk/algorithms/image_resize_classic.py
algorithm_mic_sdk/algorithms/image_search.py
algorithm_mic_sdk/algorithms/instant_id_cartoon_portrait.py
algorithm_mic_sdk/algorithms/match_face_feature.py
algorithm_mic_sdk/algorithms/music_score_recognition.py
algorithm_mic_sdk/algorithms/object_detection.py
algorithm_mic_sdk/algorithms/ocr_rec.py
algorithm_mic_sdk/algorithms/original_background_crop.py
algorithm_mic_sdk/algorithms/paper_rotation.py
algorithm_mic_sdk/algorithms/photo_to_cartoon.py
algorithm_mic_sdk/algorithms/portrait_style_pipeline.py
leqi_algorithm_mic_sdk.egg-info/PKG-INFO
leqi_algorithm_mic_sdk.egg-info/SOURCES.txt
leqi_algorithm_mic_sdk.egg-info/dependency_links.txt
leqi_algorithm_mic_sdk.egg-info/requires.txt
leqi_algorithm_mic_sdk.egg-info/top_level.txt