Metadata-Version: 2.1
Name: leqi-algorithm-mic-sdk
Version: 1.49.0
Summary: LeQi
Home-page: https://www.yuque.com/fenfendeyouzhiqingnian/algorithm
Author: panso
Author-email: panrs@venpoo.com
License: MIT
Platform: any
